OverDose.py
OverDose-0.0.2.dist-info/METADATA
OverDose-0.0.2.dist-info/WHEEL
OverDose-0.0.2.dist-info/entry_points.txt
OverDose-0.0.2.dist-info/top_level.txt
OverDose-0.0.2.dist-info/RECORD
