Metadata-Version: 2.1
Name: OverDose
Version: 0.0.2
Summary: Overdose of drugs in the US
Home-page: https://github.com/i-inose/OverDose
Author: Izuru Inose
Author-email: i.inose0304@gmail.com
Project-URL: Bug Tracker, https://github.com/i-inose/OverDose
Classifier: Programming Language :: Python :: 3
Classifier: License :: OSI Approved :: MIT License
Classifier: Operating System :: OS Independent
Requires-Python: >=3.7
